phone_scraper/__init__.py
phone_scraper/cli.py
phone_scraper/scraper.py
phone_scraper-0.1.1.dist-info/METADATA
phone_scraper-0.1.1.dist-info/WHEEL
phone_scraper-0.1.1.dist-info/top_level.txt
phone_scraper-0.1.1.dist-info/RECORD
