Metadata-Version: 2.4
Name: phone_scraper
Version: 0.1.1
Summary: Scrape smartphone data from Konga and Jumia
Author: Irechukwu Nkweke
Requires-Dist: requests
Requires-Dist: beautifulsoup4
Requires-Dist: pandas
Requires-Dist: openpyxl
Requires-Dist: selenium
Dynamic: author
Dynamic: requires-dist
Dynamic: summary
